ascii_mp4_video_player_exp/LICENSE
ascii_mp4_video_player_exp/README.md
ascii_mp4_video_player_exp/__init__.py
ascii_mp4_video_player_exp/ascii_player.py
ascii_mp4_video_player_exp-0.33.dist-info/licenses/ascii_mp4_video_player_exp/LICENSE
ascii_mp4_video_player_exp-0.33.dist-info/METADATA
ascii_mp4_video_player_exp-0.33.dist-info/WHEEL
ascii_mp4_video_player_exp-0.33.dist-info/top_level.txt
ascii_mp4_video_player_exp-0.33.dist-info/RECORD
