Metadata-Version: 2.4
Name: ascii_mp4_video_player_exp
Version: 0.33
Summary: ASCII mp4 video player experimental
Author-email: paul <paul@kfsoft.info>
Classifier: Programming Language :: Python :: 3
Classifier: License :: OSI Approved :: MIT License
Classifier: Operating System :: OS Independent
Requires-Python: >=3.10
License-File: ascii_mp4_video_player_exp/LICENSE
Requires-Dist: opencv-python
Requires-Dist: numpy
Requires-Dist: windows-curses; platform_system == "Windows"
Dynamic: license-file
